cfdtools/__init__.py
cfdtools/_cli.py
cfdtools/api.py
cfdtools/data.py
cfdtools/plot.py
cfdtools/cgns/__init__.py
cfdtools/cgns/cgns.py
cfdtools/gmsh/__init__.py
cfdtools/gmsh/_gmsh.py
cfdtools/gmsh/reader.py
cfdtools/hdf5/__init__.py
cfdtools/hdf5/_hdf5.py
cfdtools/ic3/__init__.py
cfdtools/ic3/_ic3.py
cfdtools/ic3/readerV4.py
cfdtools/ic3/reader_legacy.py
cfdtools/ic3/writerV2.py
cfdtools/ic3/writerV3.py
cfdtools/ic3/writerV4.py
cfdtools/meshbase/__init__.py
cfdtools/meshbase/_connectivity.py
cfdtools/meshbase/_elements.py
cfdtools/meshbase/_geom.py
cfdtools/meshbase/_mesh.py
cfdtools/meshbase/simple.py
cfdtools/physics/dicovar.py
cfdtools/probes/__init__.py
cfdtools/probes/data.py
cfdtools/probes/plot.py
cfdtools/utils/__init__.py
cfdtools/utils/_dev.py
cfdtools/utils/maths.py
cfdtools/utils/polybase.py
cfdtools/vtk/__init__.py
cfdtools/vtk/_vtk.py
cfdtools/vtk/_vtkList.py
cfdtools-0.6.0.dist-info/LICENSE
cfdtools-0.6.0.dist-info/METADATA
cfdtools-0.6.0.dist-info/WHEEL
cfdtools-0.6.0.dist-info/entry_points.txt
cfdtools-0.6.0.dist-info/top_level.txt
cfdtools-0.6.0.dist-info/RECORD
