Metadata-Version: 2.1
Name: cfdtools
Version: 0.6.0
Summary: Tools for mesh and solution management in CFD
Author-email: "J. Gressier" <jeremie.gressier@isae-supaero.fr>
License: MIT License
Project-URL: Homepage, https://github.com/jgressier/cfdtools
Project-URL: Documentation, https://cfdtools.readthedocs.io/en/latest/
Classifier: Development Status :: 3 - Alpha
Classifier: License :: OSI Approved :: MIT License
Classifier: Natural Language :: English
Classifier: Operating System :: OS Independent
Classifier: Programming Language :: Python
Classifier: Programming Language :: Python :: 3.7
Classifier: Programming Language :: Python :: 3.8
Classifier: Programming Language :: Python :: 3.9
Classifier: Programming Language :: Python :: 3.10
Classifier: Programming Language :: Python :: 3.11
Classifier: Programming Language :: Python :: 3.12
Classifier: Intended Audience :: Science/Research
Classifier: Topic :: Scientific/Engineering :: Physics
Classifier: Topic :: Software Development :: Libraries :: Python Modules
Requires-Python: >=3.7
License-File: LICENSE
Requires-Dist: numpy>=1.15
Requires-Dist: scipy>=1.6
Requires-Dist: h5py>=3.1
Requires-Dist: pyvista>=0.38
Provides-Extra: dev
Requires-Dist: pytest>=6.0; extra == "dev"
Requires-Dist: pytest-cov>=2.11.1; extra == "dev"
Requires-Dist: pylint>=2.6.0; extra == "dev"
Provides-Extra: doc
Requires-Dist: mkdocs>=1.1; extra == "doc"
Requires-Dist: mkdocs-material>=6.2.5; extra == "doc"
Requires-Dist: mkdocs-jupyter>=0.15; extra == "doc"
Requires-Dist: markdown-include>=0.6.0; extra == "doc"
Requires-Dist: mkdocs-include-markdown-plugin; extra == "doc"
Requires-Dist: mkdocs-exclude; extra == "doc"
